pylibmspack/__init__.py
pylibmspack/_cab.c
pylibmspack/_cab.cp310-win_amd64.pyd
pylibmspack/_libmspack.py
pylibmspack/_paths.py
pylibmspack/cab.py
pylibmspack/chm.py
pylibmspack/errors.py
pylibmspack/kwaj.py
pylibmspack/szdd.py
pylibmspack/.libs/mspack.dll
pylibmspack/vendor/__init__.py
pylibmspack/vendor/libmspack_0.10.1.orig.tar.xz
pylibmspack-0.2.0.dist-info/licenses/LICENSE
pylibmspack-0.2.0.dist-info/licenses/NOTICE
pylibmspack-0.2.0.dist-info/licenses/THIRD_PARTY_LICENSES/LGPL-2.1.txt
pylibmspack-0.2.0.dist-info/licenses/THIRD_PARTY_LICENSES/NSIS_ZLIB_LICENSE.txt
pylibmspack-0.2.0.dist-info/METADATA
pylibmspack-0.2.0.dist-info/WHEEL
pylibmspack-0.2.0.dist-info/top_level.txt
pylibmspack-0.2.0.dist-info/RECORD
