Metadata-Version: 2.4
Name: pylibmspack
Version: 0.2.0
Summary: In-process libmspack bindings for Microsoft CAB, CHM, SZDD, and KWAJ files
Author-email: Example Author <dev@example.com>
License-Expression: MIT
Project-URL: Homepage, https://github.com/bwhitn/pylibmspack
Classifier: Development Status :: 3 - Alpha
Classifier: Intended Audience :: Developers
Classifier: Operating System :: OS Independent
Classifier: Programming Language :: Python
Classifier: Programming Language :: Python :: 3
Classifier: Programming Language :: Python :: 3 :: Only
Classifier: Programming Language :: Python :: 3.9
Classifier: Programming Language :: Python :: 3.10
Classifier: Programming Language :: Python :: 3.11
Classifier: Programming Language :: Python :: 3.12
Classifier: Programming Language :: Python :: 3.13
Classifier: Programming Language :: C
Classifier: Topic :: System :: Archiving
Requires-Python: >=3.9
License-File: LICENSE
License-File: THIRD_PARTY_LICENSES/LGPL-2.1.txt
License-File: THIRD_PARTY_LICENSES/NSIS_ZLIB_LICENSE.txt
License-File: NOTICE
Provides-Extra: dev
Requires-Dist: pytest; extra == "dev"
Dynamic: license-file
